{
  "results": [
    {
      "lid": 2306,
      "signal_ts": "2026-04-29 13:54:57.313207+00:00",
      "setup_name": "Skew Charm",
      "direction": "short",
      "grade": "A+",
      "paradigm": "BOFA-PURE",
      "entry_spx": 7129.99,
      "entry_mes": 7159.25,
      "exit_mes": 7173.25,
      "exit_spx": 7123.93,
      "real_pnl_pts": -14.0,
      "portal_pnl_pts": 6.059999999999491,
      "gap_pts": -20.05999999999949,
      "portal_event": "trail",
      "real_event": "stop_filled",
      "spx_max_adv": 13.840000000000146,
      "spx_max_fav": 11.05999999999949,
      "mes_max_adv": 16.25,
      "mes_max_fav": 22.0,
      "category": "TRAIL_TAG_ADVERSE_WICK",
      "narrative": "Real broker SL fired (loss -14.0pt) while SPX portal would have exited at trail for +6.1pt. SPX-path max-adv was only 13.8pt vs SL distance 14pt."
    },
    {
      "lid": 2315,
      "signal_ts": "2026-04-29 15:22:27.457701+00:00",
      "setup_name": "Skew Charm",
      "direction": "short",
      "grade": "A+",
      "paradigm": "BOFA-PURE",
      "entry_spx": 7130.65,
      "entry_mes": 7160.5,
      "exit_mes": 7150.25,
      "exit_spx": 7123.93,
      "real_pnl_pts": 10.25,
      "portal_pnl_pts": 6.719999999999345,
      "gap_pts": 3.530000000000655,
      "portal_event": "trail",
      "real_event": "stop_filled",
      "spx_max_adv": 2.5,
      "spx_max_fav": 11.719999999999345,
      "mes_max_adv": 12.0,
      "mes_max_fav": 23.25,
      "category": "BASIS_DRIFT",
      "narrative": "Gap=+3.53pt within basis drift threshold."
    },
    {
      "lid": 2323,
      "signal_ts": "2026-04-29 16:24:57.478750+00:00",
      "setup_name": "Skew Charm",
      "direction": "short",
      "grade": "B",
      "paradigm": "BOFA-PURE",
      "entry_spx": 7123.16,
      "entry_mes": 7155.5,
      "exit_mes": 7148.0,
      "exit_spx": 7115.67,
      "real_pnl_pts": 7.5,
      "portal_pnl_pts": 7.489999999999782,
      "gap_pts": 0.010000000000218279,
      "portal_event": "trail",
      "real_event": "stop_filled",
      "spx_max_adv": 5.960000000000036,
      "spx_max_fav": 12.489999999999782,
      "mes_max_adv": 17.0,
      "mes_max_fav": 18.25,
      "category": "BASIS_DRIFT",
      "narrative": "Gap=+0.01pt within basis drift threshold."
    },
    {
      "lid": 2333,
      "signal_ts": "2026-04-29 17:31:57.509861+00:00",
      "setup_name": "Skew Charm",
      "direction": "short",
      "grade": "B",
      "paradigm": "BOFA-PURE",
      "entry_spx": 7124.64,
      "entry_mes": 7153.25,
      "exit_mes": 7143.25,
      "exit_spx": 7115.67,
      "real_pnl_pts": 10.0,
      "portal_pnl_pts": 8.970000000000255,
      "gap_pts": 1.0299999999997453,
      "portal_event": "trail",
      "real_event": "trail_market_exit",
      "spx_max_adv": 4.479999999999563,
      "spx_max_fav": 13.970000000000255,
      "mes_max_adv": 19.25,
      "mes_max_fav": 16.0,
      "category": "OUTCOME_RESOLVED",
      "narrative": "Bot market-exited at trail trigger (rare path)"
    },
    {
      "lid": 2346,
      "signal_ts": "2026-04-29 19:11:59.816423+00:00",
      "setup_name": "Skew Charm",
      "direction": "short",
      "grade": "B",
      "paradigm": "BOFA-PURE",
      "entry_spx": 7130.72,
      "entry_mes": 7160.5,
      "exit_mes": 7160.25,
      "exit_spx": 7133.58,
      "real_pnl_pts": 0.25,
      "portal_pnl_pts": -2.8599999999996726,
      "gap_pts": 3.1099999999996726,
      "portal_event": "eod",
      "real_event": "eod_flatten",
      "spx_max_adv": 6.229999999999563,
      "spx_max_fav": 4.520000000000437,
      "mes_max_adv": 12.0,
      "mes_max_fav": 6.25,
      "category": "BUG_EOD_FLATTEN",
      "narrative": "Held overnight (eod flatten). portal exit_event=eod"
    },
    {
      "lid": 2358,
      "signal_ts": "2026-04-30 14:16:59.067274+00:00",
      "setup_name": "Skew Charm",
      "direction": "long",
      "grade": "A+",
      "paradigm": "BOFA-PURE",
      "entry_spx": 7131.67,
      "entry_mes": 7159.0,
      "exit_mes": 7171.75,
      "exit_spx": 7136.88,
      "real_pnl_pts": 12.75,
      "portal_pnl_pts": 5.210000000000036,
      "gap_pts": 7.539999999999964,
      "portal_event": "trail",
      "real_event": "stop_filled",
      "spx_max_adv": 0.0,
      "spx_max_fav": 10.210000000000036,
      "mes_max_adv": 1.5,
      "mes_max_fav": 92.75,
      "category": "MES_FAVORABLE",
      "narrative": "Real outperformed SPX path by +7.54pt (MES had bigger favorable swing than SPX showed)."
    },
    {
      "lid": 2361,
      "signal_ts": "2026-04-30 14:49:59.018799+00:00",
      "setup_name": "Skew Charm",
      "direction": "long",
      "grade": "A",
      "paradigm": "BOFA-PURE",
      "entry_spx": 7151.32,
      "entry_mes": 7181.5,
      "exit_mes": 7192.5,
      "exit_spx": 7162.41,
      "real_pnl_pts": 11.0,
      "portal_pnl_pts": 11.090000000000146,
      "gap_pts": -0.09000000000014552,
      "portal_event": "trail",
      "real_event": "stop_filled",
      "spx_max_adv": 0.0,
      "spx_max_fav": 16.090000000000146,
      "mes_max_adv": 1.75,
      "mes_max_fav": 70.25,
      "category": "BASIS_DRIFT",
      "narrative": "Gap=-0.09pt within basis drift threshold."
    },
    {
      "lid": 2370,
      "signal_ts": "2026-04-30 16:41:59.072621+00:00",
      "setup_name": "Skew Charm",
      "direction": "long",
      "grade": "A",
      "paradigm": "BOFA-PURE",
      "entry_spx": 7172.37,
      "entry_mes": 7203.25,
      "exit_mes": 7215.25,
      "exit_spx": 7180.98,
      "real_pnl_pts": 12.0,
      "portal_pnl_pts": 8.609999999999673,
      "gap_pts": 3.3900000000003274,
      "portal_event": "trail",
      "real_event": "stop_filled",
      "spx_max_adv": 9.789999999999964,
      "spx_max_fav": 13.609999999999673,
      "mes_max_adv": 10.5,
      "mes_max_fav": 48.5,
      "category": "BASIS_DRIFT",
      "narrative": "Gap=+3.39pt within basis drift threshold."
    },
    {
      "lid": 2375,
      "signal_ts": "2026-04-30 17:43:01.681105+00:00",
      "setup_name": "Skew Charm",
      "direction": "long",
      "grade": "A",
      "paradigm": "BOFA-PURE",
      "entry_spx": 7187.37,
      "entry_mes": 7217.25,
      "exit_mes": 7228.5,
      "exit_spx": 7194.86,
      "real_pnl_pts": 11.25,
      "portal_pnl_pts": 7.489999999999782,
      "gap_pts": 3.7600000000002183,
      "portal_event": "trail",
      "real_event": "stop_filled",
      "spx_max_adv": 0.0,
      "spx_max_fav": 12.489999999999782,
      "mes_max_adv": 2.75,
      "mes_max_fav": 34.5,
      "category": "BASIS_DRIFT",
      "narrative": "Gap=+3.76pt within basis drift threshold."
    },
    {
      "lid": 2427,
      "signal_ts": "2026-05-01 19:11:43.264795+00:00",
      "setup_name": "Skew Charm",
      "direction": "long",
      "grade": "B",
      "paradigm": "BOFA-PURE",
      "entry_spx": 7242.45,
      "entry_mes": 7270.25,
      "exit_mes": 7271.5,
      "exit_spx": 7233.85,
      "real_pnl_pts": 1.25,
      "portal_pnl_pts": -8.599999999999454,
      "gap_pts": 9.849999999999454,
      "portal_event": "eod",
      "real_event": "eod_flatten",
      "spx_max_adv": 8.599999999999454,
      "spx_max_fav": 6.039999999999964,
      "mes_max_adv": 16.75,
      "mes_max_fav": 7.0,
      "category": "BUG_EOD_FLATTEN",
      "narrative": "Held overnight (eod flatten). portal exit_event=eod"
    },
    {
      "lid": 2433,
      "signal_ts": "2026-05-04 14:00:31.723917+00:00",
      "setup_name": "AG Short",
      "direction": "short",
      "grade": "A",
      "paradigm": "AG-LIS",
      "entry_spx": 7227.34,
      "entry_mes": 7248.75,
      "exit_mes": 7268.0,
      "exit_spx": 7218.77,
      "real_pnl_pts": -19.25,
      "portal_pnl_pts": 8.569999999999709,
      "gap_pts": -27.81999999999971,
      "portal_event": "trail",
      "real_event": "LOSS",
      "spx_max_adv": 16.849999999999454,
      "spx_max_fav": 13.569999999999709,
      "mes_max_adv": 22.25,
      "mes_max_fav": 49.25,
      "category": "TRAIL_TAG_ADVERSE_WICK",
      "narrative": "Real broker SL fired (loss -19.2pt) while SPX portal would have exited at trail for +8.6pt. SPX-path max-adv was only 16.8pt vs SL distance 20.0pt."
    },
    {
      "lid": 2434,
      "signal_ts": "2026-05-04 13:46:31.457820+00:00",
      "setup_name": "Skew Charm",
      "direction": "long",
      "grade": "B",
      "paradigm": "AG-LIS",
      "entry_spx": 7228.95,
      "entry_mes": 7253.75,
      "exit_mes": 7262.5,
      "exit_spx": 7234.99,
      "real_pnl_pts": 8.75,
      "portal_pnl_pts": 6.039999999999964,
      "gap_pts": 2.7100000000000364,
      "portal_event": "trail",
      "real_event": "stop_filled",
      "spx_max_adv": 5.579999999999927,
      "spx_max_fav": 11.039999999999964,
      "mes_max_adv": 54.25,
      "mes_max_fav": 17.25,
      "category": "BASIS_DRIFT",
      "narrative": "Gap=+2.71pt within basis drift threshold."
    },
    {
      "lid": 2442,
      "signal_ts": "2026-05-04 14:53:28.568617+00:00",
      "setup_name": "AG Short",
      "direction": "short",
      "grade": "A+",
      "paradigm": "AG-LIS",
      "entry_spx": 7243.11,
      "entry_mes": 7267.75,
      "exit_mes": 7259.25,
      "exit_spx": 7218.77,
      "real_pnl_pts": 8.5,
      "portal_pnl_pts": 24.339999999999236,
      "gap_pts": -15.839999999999236,
      "portal_event": "trail",
      "real_event": "stop_filled",
      "spx_max_adv": 0.32999999999992724,
      "spx_max_fav": 29.339999999999236,
      "mes_max_adv": 3.25,
      "mes_max_fav": 68.25,
      "category": "TRAIL_TAG_FAV_WICK",
      "narrative": "Real trail/BE fired at +8.5pt; SPX path would have run further to trail for +24.3pt. MES wick over-tightened trail."
    },
    {
      "lid": 2444,
      "signal_ts": "2026-05-04 14:56:58.510985+00:00",
      "setup_name": "Skew Charm",
      "direction": "long",
      "grade": "B",
      "paradigm": "AG-LIS",
      "entry_spx": 7236.62,
      "entry_mes": 7265.25,
      "exit_mes": 7251.25,
      "exit_spx": 7222.62,
      "real_pnl_pts": -14.0,
      "portal_pnl_pts": -14.0,
      "gap_pts": 0.0,
      "portal_event": "stop",
      "real_event": "stop_filled",
      "spx_max_adv": 22.849999999999454,
      "spx_max_fav": 0.0,
      "mes_max_adv": 65.75,
      "mes_max_fav": 1.5,
      "category": "SL_HIT_BOTH",
      "narrative": "Both initial SL. real=-14.0 portal=-14.0 gap=+0.00"
    },
    {
      "lid": 2447,
      "signal_ts": "2026-05-04 15:03:01.045759+00:00",
      "setup_name": "Skew Charm",
      "direction": "short",
      "grade": "A",
      "paradigm": "BOFA-PURE",
      "entry_spx": 7234.04,
      "entry_mes": 7261.75,
      "exit_mes": 7253.75,
      "exit_spx": 7218.77,
      "real_pnl_pts": 8.0,
      "portal_pnl_pts": 15.269999999999527,
      "gap_pts": -7.269999999999527,
      "portal_event": "trail",
      "real_event": "stop_filled",
      "spx_max_adv": 0.0,
      "spx_max_fav": 20.269999999999527,
      "mes_max_adv": 2.5,
      "mes_max_fav": 62.25,
      "category": "TRAIL_TAG_FAV_WICK",
      "narrative": "Real trail/BE fired at +8.0pt; SPX path would have run further to trail for +15.3pt. MES wick over-tightened trail."
    },
    {
      "lid": 2449,
      "signal_ts": "2026-05-04 15:34:58.525544+00:00",
      "setup_name": "Skew Charm",
      "direction": "short",
      "grade": "A",
      "paradigm": "BOFA-PURE",
      "entry_spx": 7199.71,
      "entry_mes": 7230.0,
      "exit_mes": 7230.25,
      "exit_spx": 7187.36,
      "real_pnl_pts": -0.25,
      "portal_pnl_pts": 12.350000000000364,
      "gap_pts": -12.600000000000364,
      "portal_event": "trail",
      "real_event": "stop_rejected_async",
      "spx_max_adv": 3.4600000000000364,
      "spx_max_fav": 17.350000000000364,
      "mes_max_adv": 9.75,
      "mes_max_fav": 30.5,
      "category": "BUG_STOP_REJECTED",
      "narrative": "Broker rejected stop order async \u2014 bot market-exited at -0.25. Portal would have done +12.35 via trail."
    },
    {
      "lid": 2466,
      "signal_ts": "2026-05-04 16:48:28.585912+00:00",
      "setup_name": "Skew Charm",
      "direction": "short",
      "grade": "B",
      "paradigm": "BOFA-PURE",
      "entry_spx": 7190.84,
      "entry_mes": 7217.75,
      "exit_mes": 7231.75,
      "exit_spx": 7204.84,
      "real_pnl_pts": -14.0,
      "portal_pnl_pts": -14.0,
      "gap_pts": 0.0,
      "portal_event": "stop",
      "real_event": "stop_filled",
      "spx_max_adv": 14.349999999999454,
      "spx_max_fav": 2.4899999999997817,
      "mes_max_adv": 22.0,
      "mes_max_fav": 4.75,
      "category": "SL_HIT_BOTH",
      "narrative": "Both initial SL. real=-14.0 portal=-14.0 gap=+0.00"
    },
    {
      "lid": 2470,
      "signal_ts": "2026-05-04 17:18:58.701140+00:00",
      "setup_name": "Skew Charm",
      "direction": "short",
      "grade": "B",
      "paradigm": "BOFA-PURE",
      "entry_spx": 7205.19,
      "entry_mes": 7232.0,
      "exit_mes": 7227.0,
      "exit_spx": 7196.26,
      "real_pnl_pts": 5.0,
      "portal_pnl_pts": 8.929999999999382,
      "gap_pts": -3.9299999999993815,
      "portal_event": "trail",
      "real_event": "ghost_reconcile",
      "spx_max_adv": 7.0700000000006185,
      "spx_max_fav": 13.929999999999382,
      "mes_max_adv": 7.75,
      "mes_max_fav": 14.5,
      "category": "BUG_GHOST_RECONCILE",
      "narrative": "Reconciler-recovered close; bot/broker state diverged. real_pnl=+5.00 portal=+8.93"
    },
    {
      "lid": 2473,
      "signal_ts": "2026-05-04 17:49:31.384492+00:00",
      "setup_name": "VIX Divergence",
      "direction": "long",
      "grade": "A",
      "paradigm": "BOFA-PURE",
      "entry_spx": 7205.83,
      "entry_mes": 7232.5,
      "exit_mes": 7224.5,
      "exit_spx": 7197.83,
      "real_pnl_pts": -8.0,
      "portal_pnl_pts": -8.0,
      "gap_pts": 0.0,
      "portal_event": "stop",
      "real_event": "stop_filled",
      "spx_max_adv": 10.019999999999527,
      "spx_max_fav": 6.430000000000291,
      "mes_max_adv": 15.0,
      "mes_max_fav": 7.25,
      "category": "SL_HIT_BOTH",
      "narrative": "Both initial SL. real=-8.0 portal=-8.0 gap=+0.00"
    },
    {
      "lid": 2484,
      "signal_ts": "2026-05-04 19:22:58.503349+00:00",
      "setup_name": "Skew Charm",
      "direction": "long",
      "grade": "B",
      "paradigm": "BOFA-PURE",
      "entry_spx": 7201.73,
      "entry_mes": 7226.5,
      "exit_mes": 7225.0,
      "exit_spx": 7199.27,
      "real_pnl_pts": -1.5,
      "portal_pnl_pts": -2.459999999999127,
      "gap_pts": 0.9599999999991269,
      "portal_event": "eod",
      "real_event": "eod_flatten",
      "spx_max_adv": 4.1299999999992,
      "spx_max_fav": 2.7100000000000364,
      "mes_max_adv": 3.25,
      "mes_max_fav": 5.25,
      "category": "BUG_EOD_FLATTEN",
      "narrative": "Held overnight (eod flatten). portal exit_event=eod"
    },
    {
      "lid": 2490,
      "signal_ts": "2026-05-05 14:13:00.075244+00:00",
      "setup_name": "Skew Charm",
      "direction": "short",
      "grade": "A+",
      "paradigm": "AG-PURE",
      "entry_spx": 7254.93,
      "entry_mes": 7279.75,
      "exit_mes": 7274.0,
      "exit_spx": 7248.51,
      "real_pnl_pts": 5.75,
      "portal_pnl_pts": 6.420000000000073,
      "gap_pts": -0.6700000000000728,
      "portal_event": "trail",
      "real_event": "stop_filled",
      "spx_max_adv": 0.0,
      "spx_max_fav": 11.420000000000073,
      "mes_max_adv": 20.25,
      "mes_max_fav": 12.75,
      "category": "BASIS_DRIFT",
      "narrative": "Gap=-0.67pt within basis drift threshold."
    },
    {
      "lid": 2492,
      "signal_ts": "2026-05-05 14:18:01.528434+00:00",
      "setup_name": "Skew Charm",
      "direction": "long",
      "grade": "B",
      "paradigm": "AG-LIS",
      "entry_spx": 7242.74,
      "entry_mes": 7276.5,
      "exit_mes": 7281.5,
      "exit_spx": 7252.26,
      "real_pnl_pts": 5.0,
      "portal_pnl_pts": 9.520000000000437,
      "gap_pts": -4.520000000000437,
      "portal_event": "trail",
      "real_event": "stop_filled",
      "spx_max_adv": 0.0,
      "spx_max_fav": 14.520000000000437,
      "mes_max_adv": 9.5,
      "mes_max_fav": 23.5,
      "category": "BASIS_DRIFT",
      "narrative": "Gap=-4.52pt within basis drift threshold."
    },
    {
      "lid": 2497,
      "signal_ts": "2026-05-05 14:43:30.141343+00:00",
      "setup_name": "Skew Charm",
      "direction": "short",
      "grade": "A+",
      "paradigm": "BOFA-PURE",
      "entry_spx": 7253.57,
      "entry_mes": 7279.25,
      "exit_mes": 7293.25,
      "exit_spx": 7267.57,
      "real_pnl_pts": -14.0,
      "portal_pnl_pts": -14.0,
      "gap_pts": 0.0,
      "portal_event": "stop",
      "real_event": "stop_filled",
      "spx_max_adv": 14.740000000000691,
      "spx_max_fav": 4.960000000000036,
      "mes_max_adv": 20.75,
      "mes_max_fav": 6.25,
      "category": "SL_HIT_BOTH",
      "narrative": "Both initial SL. real=-14.0 portal=-14.0 gap=+0.00"
    },
    {
      "lid": 2520,
      "signal_ts": "2026-05-05 19:10:00.113894+00:00",
      "setup_name": "Skew Charm",
      "direction": "long",
      "grade": "B",
      "paradigm": "AG-LIS",
      "entry_spx": 7271.4,
      "entry_mes": 7296.75,
      "exit_mes": 7291.5,
      "exit_spx": 7257.4,
      "real_pnl_pts": -5.25,
      "portal_pnl_pts": -14.0,
      "gap_pts": 8.75,
      "portal_event": "stop",
      "real_event": "eod_flatten",
      "spx_max_adv": 15.009999999999309,
      "spx_max_fav": 1.7000000000007276,
      "mes_max_adv": 14.0,
      "mes_max_fav": 3.25,
      "category": "BUG_EOD_FLATTEN",
      "narrative": "Held overnight (eod flatten). portal exit_event=stop"
    },
    {
      "lid": 2528,
      "signal_ts": "2026-05-06 14:03:44.148847+00:00",
      "setup_name": "Skew Charm",
      "direction": "long",
      "grade": "A+",
      "paradigm": "AG-PURE",
      "entry_spx": 7319.51,
      "entry_mes": 7345.25,
      "exit_mes": 7351.5,
      "exit_spx": 7342.69,
      "real_pnl_pts": 6.25,
      "portal_pnl_pts": 23.17999999999938,
      "gap_pts": -16.92999999999938,
      "portal_event": "trail",
      "real_event": "stop_filled",
      "spx_max_adv": 4.890000000000327,
      "spx_max_fav": 28.17999999999938,
      "mes_max_adv": 8.75,
      "mes_max_fav": 50.75,
      "category": "TRAIL_TAG_FAV_WICK",
      "narrative": "Real trail/BE fired at +6.2pt; SPX path would have run further to trail for +23.2pt. MES wick over-tightened trail."
    },
    {
      "lid": 2530,
      "signal_ts": "2026-05-06 14:49:10.125206+00:00",
      "setup_name": "ES Absorption",
      "direction": "bearish",
      "grade": "C",
      "paradigm": "AG-PURE",
      "entry_spx": 7340.14,
      "entry_mes": 7354.5,
      "exit_mes": 7355.0,
      "exit_spx": 7334.91,
      "real_pnl_pts": -0.5,
      "portal_pnl_pts": 5.230000000000473,
      "gap_pts": -5.730000000000473,
      "portal_event": "trail",
      "real_event": "stop_filled",
      "spx_max_adv": 7.549999999999272,
      "spx_max_fav": 8.230000000000473,
      "mes_max_adv": 41.5,
      "mes_max_fav": -0.25,
      "category": "TRAIL_TAG_FAV_WICK",
      "narrative": "Real trail/BE fired at -0.5pt; SPX path would have run further to trail for +5.2pt. MES wick over-tightened trail."
    },
    {
      "lid": 2532,
      "signal_ts": "2026-05-06 14:33:09.921967+00:00",
      "setup_name": "AG Short",
      "direction": "short",
      "grade": "A",
      "paradigm": "AG-PURE",
      "entry_spx": 7330.73,
      "entry_mes": 7359.0,
      "exit_mes": 7379.75,
      "exit_spx": 7350.73,
      "real_pnl_pts": -20.75,
      "portal_pnl_pts": -20.0,
      "gap_pts": -0.75,
      "portal_event": "stop",
      "real_event": "LOSS",
      "spx_max_adv": 22.13000000000011,
      "spx_max_fav": 0.0,
      "mes_max_adv": 37.0,
      "mes_max_fav": 4.25,
      "category": "SL_HIT_BOTH",
      "narrative": "Both initial SL. real=-20.8 portal=-20.0 gap=-0.75"
    },
    {
      "lid": 2540,
      "signal_ts": "2026-05-06 15:17:10.075511+00:00",
      "setup_name": "Skew Charm",
      "direction": "long",
      "grade": "A",
      "paradigm": "BOFA-PURE",
      "entry_spx": 7342.2,
      "entry_mes": 7368.0,
      "exit_mes": 7378.75,
      "exit_spx": 7352.07,
      "real_pnl_pts": 10.75,
      "portal_pnl_pts": 9.86999999999989,
      "gap_pts": 0.8800000000001091,
      "portal_event": "trail",
      "real_event": "stop_filled",
      "spx_max_adv": 10.289999999999964,
      "spx_max_fav": 14.86999999999989,
      "mes_max_adv": 13.25,
      "mes_max_fav": 28.0,
      "category": "BASIS_DRIFT",
      "narrative": "Gap=+0.88pt within basis drift threshold."
    },
    {
      "lid": 2565,
      "signal_ts": "2026-05-07 13:50:50.404396+00:00",
      "setup_name": "Skew Charm",
      "direction": "short",
      "grade": "A",
      "paradigm": "BOFA-PURE",
      "entry_spx": 7361.43,
      "entry_mes": 7385.5,
      "exit_mes": 7399.5,
      "exit_spx": 7375.43,
      "real_pnl_pts": -14.0,
      "portal_pnl_pts": -14.0,
      "gap_pts": 0.0,
      "portal_event": "stop",
      "real_event": "stop_filled",
      "spx_max_adv": 14.25,
      "spx_max_fav": 0.0,
      "mes_max_adv": 24.5,
      "mes_max_fav": 39.75,
      "category": "SL_HIT_BOTH",
      "narrative": "Both initial SL. real=-14.0 portal=-14.0 gap=+0.00"
    },
    {
      "lid": 2575,
      "signal_ts": "2026-05-07 15:01:20.633942+00:00",
      "setup_name": "Skew Charm",
      "direction": "long",
      "grade": "A+",
      "paradigm": "BOFA-PURE",
      "entry_spx": 7383.15,
      "entry_mes": 7407.25,
      "exit_mes": 7393.25,
      "exit_spx": 7369.15,
      "real_pnl_pts": -14.0,
      "portal_pnl_pts": -14.0,
      "gap_pts": 0.0,
      "portal_event": "stop",
      "real_event": "stop_filled",
      "spx_max_adv": 14.779999999999745,
      "spx_max_fav": 0.020000000000436557,
      "mes_max_adv": 61.5,
      "mes_max_fav": 2.75,
      "category": "SL_HIT_BOTH",
      "narrative": "Both initial SL. real=-14.0 portal=-14.0 gap=+0.00"
    },
    {
      "lid": 2644,
      "signal_ts": "2026-05-08 18:47:30.032622+00:00",
      "setup_name": "ES Absorption",
      "direction": "bullish",
      "grade": "A",
      "paradigm": "BOFA-PURE",
      "entry_spx": 7392.11,
      "entry_mes": 7416.75,
      "exit_mes": 7408.75,
      "exit_spx": 7397.27,
      "real_pnl_pts": -8.0,
      "portal_pnl_pts": 5.160000000000764,
      "gap_pts": -13.160000000000764,
      "portal_event": "eod",
      "real_event": "stop_filled",
      "spx_max_adv": 6.649999999999636,
      "spx_max_fav": 5.160000000000764,
      "mes_max_adv": 9.0,
      "mes_max_fav": 5.5,
      "category": "TRAIL_TAG_ADVERSE_WICK",
      "narrative": "Real broker SL fired (loss -8.0pt) while SPX portal would have exited at eod for +5.2pt. SPX-path max-adv was only 6.6pt vs SL distance 8pt."
    },
    {
      "lid": 2646,
      "signal_ts": "2026-05-08 19:04:49.820634+00:00",
      "setup_name": "ES Absorption",
      "direction": "bullish",
      "grade": "A",
      "paradigm": "BOFA-PURE",
      "entry_spx": 7388.28,
      "entry_mes": 7412.75,
      "exit_mes": 7417.75,
      "exit_spx": 7397.27,
      "real_pnl_pts": 5.0,
      "portal_pnl_pts": 8.990000000000691,
      "gap_pts": -3.990000000000691,
      "portal_event": "eod",
      "real_event": "outcome_resolved_win",
      "spx_max_adv": 0.0,
      "spx_max_fav": 8.990000000000691,
      "mes_max_adv": 2.5,
      "mes_max_fav": 9.5,
      "category": "OUTCOME_RESOLVED",
      "narrative": "Outcome tracker resolved (outcome_resolved_win), broker stop never fired. real=5.0 portal=+8.99"
    },
    {
      "lid": 2651,
      "signal_ts": "2026-05-11 13:46:13.329719+00:00",
      "setup_name": "Skew Charm",
      "direction": "short",
      "grade": "A+",
      "paradigm": "GEX-PURE",
      "entry_spx": 7409.76,
      "entry_mes": 7433.5,
      "exit_mes": 7427.0,
      "exit_spx": 7423.76,
      "real_pnl_pts": 6.5,
      "portal_pnl_pts": -14.0,
      "gap_pts": 20.5,
      "portal_event": "stop",
      "real_event": "stop_filled",
      "spx_max_adv": 14.75,
      "spx_max_fav": 6.9099999999998545,
      "mes_max_adv": 21.25,
      "mes_max_fav": 11.75,
      "category": "MES_FAVORABLE",
      "narrative": "Real outperformed SPX path by +20.50pt (MES had bigger favorable swing than SPX showed)."
    },
    {
      "lid": 2657,
      "signal_ts": "2026-05-11 14:47:43.433871+00:00",
      "setup_name": "Skew Charm",
      "direction": "short",
      "grade": "A+",
      "paradigm": "GEX-PURE",
      "entry_spx": 7411.58,
      "entry_mes": 7435.0,
      "exit_mes": 7449.0,
      "exit_spx": 7425.58,
      "real_pnl_pts": -14.0,
      "portal_pnl_pts": -14.0,
      "gap_pts": 0.0,
      "portal_event": "stop",
      "real_event": "stop_filled",
      "spx_max_adv": 15.430000000000291,
      "spx_max_fav": 2.1899999999996,
      "mes_max_adv": 19.75,
      "mes_max_fav": 7.25,
      "category": "SL_HIT_BOTH",
      "narrative": "Both initial SL. real=-14.0 portal=-14.0 gap=+0.00"
    },
    {
      "lid": 2684,
      "signal_ts": "2026-05-12 13:47:57.441775+00:00",
      "setup_name": "Skew Charm",
      "direction": "long",
      "grade": "A+",
      "paradigm": "BofA-LIS",
      "entry_spx": 7379.98,
      "entry_mes": 7403.0,
      "exit_mes": 7389.0,
      "exit_spx": 7365.98,
      "real_pnl_pts": -14.0,
      "portal_pnl_pts": -14.0,
      "gap_pts": 0.0,
      "portal_event": "stop",
      "real_event": "stop_filled",
      "spx_max_adv": 19.539999999999964,
      "spx_max_fav": 4.5,
      "mes_max_adv": 39.5,
      "mes_max_fav": 31.0,
      "category": "SL_HIT_BOTH",
      "narrative": "Both initial SL. real=-14.0 portal=-14.0 gap=+0.00"
    },
    {
      "lid": 2696,
      "signal_ts": "2026-05-12 14:57:28.302875+00:00",
      "setup_name": "Skew Charm",
      "direction": "long",
      "grade": "A+",
      "paradigm": "AG-PURE",
      "entry_spx": 7357.79,
      "entry_mes": 7382.25,
      "exit_mes": 7368.25,
      "exit_spx": 7343.79,
      "real_pnl_pts": -14.0,
      "portal_pnl_pts": -14.0,
      "gap_pts": 0.0,
      "portal_event": "stop",
      "real_event": "ghost_reconcile",
      "spx_max_adv": 18.31999999999971,
      "spx_max_fav": 3.3299999999999272,
      "mes_max_adv": 18.75,
      "mes_max_fav": 51.75,
      "category": "BUG_GHOST_RECONCILE",
      "narrative": "Reconciler-recovered close; bot/broker state diverged. real_pnl=-14.00 portal=-14.00"
    },
    {
      "lid": 2697,
      "signal_ts": "2026-05-12 15:32:51.494017+00:00",
      "setup_name": "ES Absorption",
      "direction": "bullish",
      "grade": "A",
      "paradigm": "AG-PURE",
      "entry_spx": 7348.63,
      "entry_mes": 7371.5,
      "exit_mes": 7376.75,
      "exit_spx": 7354.76,
      "real_pnl_pts": 5.25,
      "portal_pnl_pts": 6.130000000000109,
      "gap_pts": -0.8800000000001091,
      "portal_event": "trail",
      "real_event": "outcome_resolved_win",
      "spx_max_adv": 0.819999999999709,
      "spx_max_fav": 9.13000000000011,
      "mes_max_adv": 7.75,
      "mes_max_fav": 62.5,
      "category": "OUTCOME_RESOLVED",
      "narrative": "Outcome tracker resolved (outcome_resolved_win), broker stop never fired. real=5.25 portal=+6.13"
    },
    {
      "lid": 2705,
      "signal_ts": "2026-05-12 15:58:55.741364+00:00",
      "setup_name": "Skew Charm",
      "direction": "long",
      "grade": "A",
      "paradigm": "BOFA-PURE",
      "entry_spx": 7346.69,
      "entry_mes": 7371.0,
      "exit_mes": 7387.5,
      "exit_spx": 7379.84,
      "real_pnl_pts": 16.5,
      "portal_pnl_pts": 33.150000000000546,
      "gap_pts": -16.650000000000546,
      "portal_event": "trail",
      "real_event": "stop_filled",
      "spx_max_adv": 7.589999999999236,
      "spx_max_fav": 38.150000000000546,
      "mes_max_adv": 7.25,
      "mes_max_fav": 63.0,
      "category": "TRAIL_TAG_FAV_WICK",
      "narrative": "Real trail/BE fired at +16.5pt; SPX path would have run further to trail for +33.2pt. MES wick over-tightened trail."
    },
    {
      "lid": 2707,
      "signal_ts": "2026-05-12 16:15:41.716769+00:00",
      "setup_name": "VIX Divergence",
      "direction": "long",
      "grade": "A+",
      "paradigm": "AG-LIS",
      "entry_spx": 7352.49,
      "entry_mes": 7376.75,
      "exit_mes": 7363.75,
      "exit_spx": 7344.49,
      "real_pnl_pts": -13.0,
      "portal_pnl_pts": -8.0,
      "gap_pts": -5.0,
      "portal_event": "stop",
      "real_event": "stop_filled",
      "spx_max_adv": 8.039999999999964,
      "spx_max_fav": 0.7399999999997817,
      "mes_max_adv": 13.0,
      "mes_max_fav": 57.25,
      "category": "SL_HIT_BOTH",
      "narrative": "Both initial SL. real=-13.0 portal=-8.0 gap=-5.00"
    },
    {
      "lid": 2713,
      "signal_ts": "2026-05-12 17:11:44.657252+00:00",
      "setup_name": "Skew Charm",
      "direction": "long",
      "grade": "B",
      "paradigm": "BOFA-PURE",
      "entry_spx": 7353.2,
      "entry_mes": 7378.0,
      "exit_mes": 7387.75,
      "exit_spx": 7379.84,
      "real_pnl_pts": 9.75,
      "portal_pnl_pts": 26.640000000000327,
      "gap_pts": -16.890000000000327,
      "portal_event": "trail",
      "real_event": "stop_filled",
      "spx_max_adv": 0.5900000000001455,
      "spx_max_fav": 31.640000000000327,
      "mes_max_adv": 3.25,
      "mes_max_fav": 56.0,
      "category": "TRAIL_TAG_FAV_WICK",
      "narrative": "Real trail/BE fired at +9.8pt; SPX path would have run further to trail for +26.6pt. MES wick over-tightened trail."
    },
    {
      "lid": 2716,
      "signal_ts": "2026-05-12 17:43:44.572622+00:00",
      "setup_name": "Skew Charm",
      "direction": "long",
      "grade": "B",
      "paradigm": "BOFA-PURE",
      "entry_spx": 7367.96,
      "entry_mes": 7393.5,
      "exit_mes": 7405.25,
      "exit_spx": 7379.84,
      "real_pnl_pts": 11.75,
      "portal_pnl_pts": 11.88000000000011,
      "gap_pts": -0.13000000000010914,
      "portal_event": "trail",
      "real_event": "stop_filled",
      "spx_max_adv": 2.480000000000473,
      "spx_max_fav": 16.88000000000011,
      "mes_max_adv": 4.0,
      "mes_max_fav": 40.5,
      "category": "BASIS_DRIFT",
      "narrative": "Gap=-0.13pt within basis drift threshold."
    },
    {
      "lid": 2718,
      "signal_ts": "2026-05-12 18:20:14.904308+00:00",
      "setup_name": "Skew Charm",
      "direction": "long",
      "grade": "A",
      "paradigm": "BOFA-PURE",
      "entry_spx": 7374.64,
      "entry_mes": 7397.75,
      "exit_mes": 7405.0,
      "exit_spx": 7379.84,
      "real_pnl_pts": 7.25,
      "portal_pnl_pts": 5.199999999999818,
      "gap_pts": 2.050000000000182,
      "portal_event": "trail",
      "real_event": "stop_filled",
      "spx_max_adv": 0.0,
      "spx_max_fav": 10.199999999999818,
      "mes_max_adv": 2.5,
      "mes_max_fav": 36.25,
      "category": "BASIS_DRIFT",
      "narrative": "Gap=+2.05pt within basis drift threshold."
    },
    {
      "lid": 2726,
      "signal_ts": "2026-05-12 19:20:11.629470+00:00",
      "setup_name": "AG Short",
      "direction": "short",
      "grade": "C",
      "paradigm": "AG-LIS",
      "entry_spx": 7387.66,
      "entry_mes": 7414.0,
      "exit_mes": 7428.75,
      "exit_spx": 7402.41,
      "real_pnl_pts": -14.75,
      "portal_pnl_pts": -14.75,
      "gap_pts": 0.0,
      "portal_event": "stop",
      "real_event": "eod_flatten",
      "spx_max_adv": 17.960000000000036,
      "spx_max_fav": 0.6099999999996726,
      "mes_max_adv": 20.0,
      "mes_max_fav": 3.5,
      "category": "BUG_EOD_FLATTEN",
      "narrative": "Held overnight (eod flatten). portal exit_event=stop"
    },
    {
      "lid": 2728,
      "signal_ts": "2026-05-12 19:24:11.626891+00:00",
      "setup_name": "Skew Charm",
      "direction": "long",
      "grade": "B",
      "paradigm": "AG-LIS",
      "entry_spx": 7391.13,
      "entry_mes": 7413.0,
      "exit_mes": 7421.75,
      "exit_spx": 7403.91,
      "real_pnl_pts": 8.75,
      "portal_pnl_pts": 12.779999999999745,
      "gap_pts": -4.029999999999745,
      "portal_event": "trail",
      "real_event": "ghost_reconcile",
      "spx_max_adv": 0.0,
      "spx_max_fav": 17.779999999999745,
      "mes_max_adv": 2.5,
      "mes_max_fav": 21.0,
      "category": "BUG_GHOST_RECONCILE",
      "narrative": "Reconciler-recovered close; bot/broker state diverged. real_pnl=+8.75 portal=+12.78"
    },
    {
      "lid": 2730,
      "signal_ts": "2026-05-13 13:45:17.280973+00:00",
      "setup_name": "Skew Charm",
      "direction": "long",
      "grade": "A",
      "paradigm": "BOFA-PURE",
      "entry_spx": 7387.39,
      "entry_mes": 7411.25,
      "exit_mes": 7418.0,
      "exit_spx": 7393.94,
      "real_pnl_pts": 6.75,
      "portal_pnl_pts": 6.549999999999272,
      "gap_pts": 0.2000000000007276,
      "portal_event": "trail",
      "real_event": "stop_filled",
      "spx_max_adv": 6.300000000000182,
      "spx_max_fav": 11.549999999999272,
      "mes_max_adv": 12.0,
      "mes_max_fav": 72.75,
      "category": "BASIS_DRIFT",
      "narrative": "Gap=+0.20pt within basis drift threshold."
    },
    {
      "lid": 2733,
      "signal_ts": "2026-05-13 14:04:57.223950+00:00",
      "setup_name": "ES Absorption",
      "direction": "bullish",
      "grade": "A",
      "paradigm": "SIDIAL-EXTREME",
      "entry_spx": 7395.73,
      "entry_mes": 7416.5,
      "exit_mes": 7417.25,
      "exit_spx": 7400.8,
      "real_pnl_pts": 0.75,
      "portal_pnl_pts": 5.0700000000006185,
      "gap_pts": -4.3200000000006185,
      "portal_event": "trail",
      "real_event": "ghost_reconcile",
      "spx_max_adv": 3.009999999999309,
      "spx_max_fav": 8.070000000000618,
      "mes_max_adv": 3.0,
      "mes_max_fav": 67.5,
      "category": "BUG_GHOST_RECONCILE",
      "narrative": "Reconciler-recovered close; bot/broker state diverged. real_pnl=+0.75 portal=+5.07"
    },
    {
      "lid": 2735,
      "signal_ts": "2026-05-13 14:12:17.062475+00:00",
      "setup_name": "ES Absorption",
      "direction": "bearish",
      "grade": "A+",
      "paradigm": "SIDIAL-EXTREME",
      "entry_spx": 7396.61,
      "entry_mes": 7414.25,
      "exit_mes": 7430.25,
      "exit_spx": 7404.61,
      "real_pnl_pts": -16.0,
      "portal_pnl_pts": -8.0,
      "gap_pts": -8.0,
      "portal_event": "stop",
      "real_event": "stop_filled",
      "spx_max_adv": 9.510000000000218,
      "spx_max_fav": 3.1599999999998545,
      "mes_max_adv": 69.75,
      "mes_max_fav": 0.0,
      "category": "SL_HIT_BOTH",
      "narrative": "Both initial SL. real=-16.0 portal=-8.0 gap=-8.00"
    },
    {
      "lid": 2737,
      "signal_ts": "2026-05-13 14:22:12.618271+00:00",
      "setup_name": "ES Absorption",
      "direction": "bearish",
      "grade": "A+",
      "paradigm": "SIDIAL-EXTREME",
      "entry_spx": 7403.8,
      "entry_mes": 7422.0,
      "exit_mes": 7427.5,
      "exit_spx": 7411.8,
      "real_pnl_pts": -5.5,
      "portal_pnl_pts": -8.0,
      "gap_pts": 2.5,
      "portal_event": "stop",
      "real_event": "stop_filled",
      "spx_max_adv": 9.069999999999709,
      "spx_max_fav": 3.2600000000002183,
      "mes_max_adv": 62.0,
      "mes_max_fav": 1.25,
      "category": "BASIS_DRIFT",
      "narrative": "Gap=+2.50pt within basis drift threshold."
    },
    {
      "lid": 2740,
      "signal_ts": "2026-05-13 15:42:27.222585+00:00",
      "setup_name": "ES Absorption",
      "direction": "bearish",
      "grade": "A",
      "paradigm": "SIDIAL-EXTREME",
      "entry_spx": 7423.76,
      "entry_mes": 7444.75,
      "exit_mes": 7445.0,
      "exit_spx": 7423.76,
      "real_pnl_pts": -0.25,
      "portal_pnl_pts": 0.0,
      "gap_pts": -0.25,
      "portal_event": "breakeven",
      "real_event": "outcome_resolved_loss",
      "spx_max_adv": 0.0999999999994543,
      "spx_max_fav": 6.400000000000546,
      "mes_max_adv": 39.25,
      "mes_max_fav": 4.75,
      "category": "OUTCOME_RESOLVED",
      "narrative": "Outcome tracker resolved (outcome_resolved_loss), broker stop never fired. real=-0.25 portal=+0.00"
    },
    {
      "lid": 2744,
      "signal_ts": "2026-05-13 15:54:26.497123+00:00",
      "setup_name": "Skew Charm",
      "direction": "long",
      "grade": "A+",
      "paradigm": "BOFA-PURE",
      "entry_spx": 7418.41,
      "entry_mes": 7444.5,
      "exit_mes": 7458.25,
      "exit_spx": 7432.62,
      "real_pnl_pts": 13.75,
      "portal_pnl_pts": 14.210000000000036,
      "gap_pts": -0.4600000000000364,
      "portal_event": "trail",
      "real_event": "stop_filled",
      "spx_max_adv": 1.050000000000182,
      "spx_max_fav": 19.210000000000036,
      "mes_max_adv": 4.5,
      "mes_max_fav": 39.5,
      "category": "BASIS_DRIFT",
      "narrative": "Gap=-0.46pt within basis drift threshold."
    },
    {
      "lid": 2748,
      "signal_ts": "2026-05-13 16:28:59.455927+00:00",
      "setup_name": "AG Short",
      "direction": "short",
      "grade": "C",
      "paradigm": "AG-LIS",
      "entry_spx": 7438.62,
      "entry_mes": 7464.25,
      "exit_mes": 7479.0,
      "exit_spx": 7453.37,
      "real_pnl_pts": -14.75,
      "portal_pnl_pts": -14.75,
      "gap_pts": 0.0,
      "portal_event": "stop",
      "real_event": "stop_filled",
      "spx_max_adv": 19.890000000000327,
      "spx_max_fav": 1.5299999999997453,
      "mes_max_adv": 19.75,
      "mes_max_fav": 5.25,
      "category": "SL_HIT_BOTH",
      "narrative": "Both initial SL. real=-14.8 portal=-14.8 gap=+0.00"
    },
    {
      "lid": 2759,
      "signal_ts": "2026-05-13 18:14:56.430319+00:00",
      "setup_name": "AG Short",
      "direction": "short",
      "grade": "B",
      "paradigm": "AG-LIS",
      "entry_spx": 7458.51,
      "entry_mes": 7478.0,
      "exit_mes": 7482.0,
      "exit_spx": 7451.05,
      "real_pnl_pts": -4.0,
      "portal_pnl_pts": 7.460000000000036,
      "gap_pts": -11.460000000000036,
      "portal_event": "trail",
      "real_event": "ghost_reconcile",
      "spx_max_adv": 0.3899999999994179,
      "spx_max_fav": 12.460000000000036,
      "mes_max_adv": 6.0,
      "mes_max_fav": 11.25,
      "category": "BUG_GHOST_RECONCILE",
      "narrative": "Reconciler-recovered close; bot/broker state diverged. real_pnl=-4.00 portal=+7.46"
    }
  ],
  "arch": [
    {
      "lid": 2306,
      "signal_ts": "2026-04-29 13:54:57.313207+00:00",
      "setup_name": "Skew Charm",
      "direction": "short",
      "grade": "A+",
      "paradigm": "BOFA-PURE",
      "entry_spx": 7129.99,
      "entry_mes": 7159.25,
      "exit_mes": 7173.25,
      "exit_spx": 7123.93,
      "real_pnl_pts": -14.0,
      "portal_pnl_pts": 6.059999999999491,
      "gap_pts": -20.05999999999949,
      "portal_event": "trail",
      "real_event": "stop_filled",
      "spx_max_adv": 13.840000000000146,
      "spx_max_fav": 11.05999999999949,
      "mes_max_adv": 16.25,
      "mes_max_fav": 22.0,
      "category": "TRAIL_TAG_ADVERSE_WICK",
      "narrative": "Real broker SL fired (loss -14.0pt) while SPX portal would have exited at trail for +6.1pt. SPX-path max-adv was only 13.8pt vs SL distance 14pt.",
      "arch_pnl_pts": 5.559999999999491,
      "arch_note": "SPX-trail market-exit @ portal_event=trail, slippage=0.5pt"
    },
    {
      "lid": 2315,
      "signal_ts": "2026-04-29 15:22:27.457701+00:00",
      "setup_name": "Skew Charm",
      "direction": "short",
      "grade": "A+",
      "paradigm": "BOFA-PURE",
      "entry_spx": 7130.65,
      "entry_mes": 7160.5,
      "exit_mes": 7150.25,
      "exit_spx": 7123.93,
      "real_pnl_pts": 10.25,
      "portal_pnl_pts": 6.719999999999345,
      "gap_pts": 3.530000000000655,
      "portal_event": "trail",
      "real_event": "stop_filled",
      "spx_max_adv": 2.5,
      "spx_max_fav": 11.719999999999345,
      "mes_max_adv": 12.0,
      "mes_max_fav": 23.25,
      "category": "BASIS_DRIFT",
      "narrative": "Gap=+3.53pt within basis drift threshold.",
      "arch_pnl_pts": 10.25,
      "arch_note": "small basis drift only"
    },
    {
      "lid": 2323,
      "signal_ts": "2026-04-29 16:24:57.478750+00:00",
      "setup_name": "Skew Charm",
      "direction": "short",
      "grade": "B",
      "paradigm": "BOFA-PURE",
      "entry_spx": 7123.16,
      "entry_mes": 7155.5,
      "exit_mes": 7148.0,
      "exit_spx": 7115.67,
      "real_pnl_pts": 7.5,
      "portal_pnl_pts": 7.489999999999782,
      "gap_pts": 0.010000000000218279,
      "portal_event": "trail",
      "real_event": "stop_filled",
      "spx_max_adv": 5.960000000000036,
      "spx_max_fav": 12.489999999999782,
      "mes_max_adv": 17.0,
      "mes_max_fav": 18.25,
      "category": "BASIS_DRIFT",
      "narrative": "Gap=+0.01pt within basis drift threshold.",
      "arch_pnl_pts": 7.5,
      "arch_note": "small basis drift only"
    },
    {
      "lid": 2333,
      "signal_ts": "2026-04-29 17:31:57.509861+00:00",
      "setup_name": "Skew Charm",
      "direction": "short",
      "grade": "B",
      "paradigm": "BOFA-PURE",
      "entry_spx": 7124.64,
      "entry_mes": 7153.25,
      "exit_mes": 7143.25,
      "exit_spx": 7115.67,
      "real_pnl_pts": 10.0,
      "portal_pnl_pts": 8.970000000000255,
      "gap_pts": 1.0299999999997453,
      "portal_event": "trail",
      "real_event": "trail_market_exit",
      "spx_max_adv": 4.479999999999563,
      "spx_max_fav": 13.970000000000255,
      "mes_max_adv": 19.25,
      "mes_max_fav": 16.0,
      "category": "OUTCOME_RESOLVED",
      "narrative": "Bot market-exited at trail trigger (rare path)",
      "arch_pnl_pts": 10.0,
      "arch_note": "out of scope (broker bug or outcome tracker)"
    },
    {
      "lid": 2346,
      "signal_ts": "2026-04-29 19:11:59.816423+00:00",
      "setup_name": "Skew Charm",
      "direction": "short",
      "grade": "B",
      "paradigm": "BOFA-PURE",
      "entry_spx": 7130.72,
      "entry_mes": 7160.5,
      "exit_mes": 7160.25,
      "exit_spx": 7133.58,
      "real_pnl_pts": 0.25,
      "portal_pnl_pts": -2.8599999999996726,
      "gap_pts": 3.1099999999996726,
      "portal_event": "eod",
      "real_event": "eod_flatten",
      "spx_max_adv": 6.229999999999563,
      "spx_max_fav": 4.520000000000437,
      "mes_max_adv": 12.0,
      "mes_max_fav": 6.25,
      "category": "BUG_EOD_FLATTEN",
      "narrative": "Held overnight (eod flatten). portal exit_event=eod",
      "arch_pnl_pts": 0.25,
      "arch_note": "out of scope (broker bug or outcome tracker)"
    },
    {
      "lid": 2358,
      "signal_ts": "2026-04-30 14:16:59.067274+00:00",
      "setup_name": "Skew Charm",
      "direction": "long",
      "grade": "A+",
      "paradigm": "BOFA-PURE",
      "entry_spx": 7131.67,
      "entry_mes": 7159.0,
      "exit_mes": 7171.75,
      "exit_spx": 7136.88,
      "real_pnl_pts": 12.75,
      "portal_pnl_pts": 5.210000000000036,
      "gap_pts": 7.539999999999964,
      "portal_event": "trail",
      "real_event": "stop_filled",
      "spx_max_adv": 0.0,
      "spx_max_fav": 10.210000000000036,
      "mes_max_adv": 1.5,
      "mes_max_fav": 92.75,
      "category": "MES_FAVORABLE",
      "narrative": "Real outperformed SPX path by +7.54pt (MES had bigger favorable swing than SPX showed).",
      "arch_pnl_pts": 12.75,
      "arch_note": "fallback"
    },
    {
      "lid": 2361,
      "signal_ts": "2026-04-30 14:49:59.018799+00:00",
      "setup_name": "Skew Charm",
      "direction": "long",
      "grade": "A",
      "paradigm": "BOFA-PURE",
      "entry_spx": 7151.32,
      "entry_mes": 7181.5,
      "exit_mes": 7192.5,
      "exit_spx": 7162.41,
      "real_pnl_pts": 11.0,
      "portal_pnl_pts": 11.090000000000146,
      "gap_pts": -0.09000000000014552,
      "portal_event": "trail",
      "real_event": "stop_filled",
      "spx_max_adv": 0.0,
      "spx_max_fav": 16.090000000000146,
      "mes_max_adv": 1.75,
      "mes_max_fav": 70.25,
      "category": "BASIS_DRIFT",
      "narrative": "Gap=-0.09pt within basis drift threshold.",
      "arch_pnl_pts": 11.0,
      "arch_note": "small basis drift only"
    },
    {
      "lid": 2370,
      "signal_ts": "2026-04-30 16:41:59.072621+00:00",
      "setup_name": "Skew Charm",
      "direction": "long",
      "grade": "A",
      "paradigm": "BOFA-PURE",
      "entry_spx": 7172.37,
      "entry_mes": 7203.25,
      "exit_mes": 7215.25,
      "exit_spx": 7180.98,
      "real_pnl_pts": 12.0,
      "portal_pnl_pts": 8.609999999999673,
      "gap_pts": 3.3900000000003274,
      "portal_event": "trail",
      "real_event": "stop_filled",
      "spx_max_adv": 9.789999999999964,
      "spx_max_fav": 13.609999999999673,
      "mes_max_adv": 10.5,
      "mes_max_fav": 48.5,
      "category": "BASIS_DRIFT",
      "narrative": "Gap=+3.39pt within basis drift threshold.",
      "arch_pnl_pts": 12.0,
      "arch_note": "small basis drift only"
    },
    {
      "lid": 2375,
      "signal_ts": "2026-04-30 17:43:01.681105+00:00",
      "setup_name": "Skew Charm",
      "direction": "long",
      "grade": "A",
      "paradigm": "BOFA-PURE",
      "entry_spx": 7187.37,
      "entry_mes": 7217.25,
      "exit_mes": 7228.5,
      "exit_spx": 7194.86,
      "real_pnl_pts": 11.25,
      "portal_pnl_pts": 7.489999999999782,
      "gap_pts": 3.7600000000002183,
      "portal_event": "trail",
      "real_event": "stop_filled",
      "spx_max_adv": 0.0,
      "spx_max_fav": 12.489999999999782,
      "mes_max_adv": 2.75,
      "mes_max_fav": 34.5,
      "category": "BASIS_DRIFT",
      "narrative": "Gap=+3.76pt within basis drift threshold.",
      "arch_pnl_pts": 11.25,
      "arch_note": "small basis drift only"
    },
    {
      "lid": 2427,
      "signal_ts": "2026-05-01 19:11:43.264795+00:00",
      "setup_name": "Skew Charm",
      "direction": "long",
      "grade": "B",
      "paradigm": "BOFA-PURE",
      "entry_spx": 7242.45,
      "entry_mes": 7270.25,
      "exit_mes": 7271.5,
      "exit_spx": 7233.85,
      "real_pnl_pts": 1.25,
      "portal_pnl_pts": -8.599999999999454,
      "gap_pts": 9.849999999999454,
      "portal_event": "eod",
      "real_event": "eod_flatten",
      "spx_max_adv": 8.599999999999454,
      "spx_max_fav": 6.039999999999964,
      "mes_max_adv": 16.75,
      "mes_max_fav": 7.0,
      "category": "BUG_EOD_FLATTEN",
      "narrative": "Held overnight (eod flatten). portal exit_event=eod",
      "arch_pnl_pts": 1.25,
      "arch_note": "out of scope (broker bug or outcome tracker)"
    },
    {
      "lid": 2433,
      "signal_ts": "2026-05-04 14:00:31.723917+00:00",
      "setup_name": "AG Short",
      "direction": "short",
      "grade": "A",
      "paradigm": "AG-LIS",
      "entry_spx": 7227.34,
      "entry_mes": 7248.75,
      "exit_mes": 7268.0,
      "exit_spx": 7218.77,
      "real_pnl_pts": -19.25,
      "portal_pnl_pts": 8.569999999999709,
      "gap_pts": -27.81999999999971,
      "portal_event": "trail",
      "real_event": "LOSS",
      "spx_max_adv": 16.849999999999454,
      "spx_max_fav": 13.569999999999709,
      "mes_max_adv": 22.25,
      "mes_max_fav": 49.25,
      "category": "TRAIL_TAG_ADVERSE_WICK",
      "narrative": "Real broker SL fired (loss -19.2pt) while SPX portal would have exited at trail for +8.6pt. SPX-path max-adv was only 16.8pt vs SL distance 20.0pt.",
      "arch_pnl_pts": 8.069999999999709,
      "arch_note": "SPX-trail market-exit @ portal_event=trail, slippage=0.5pt"
    },
    {
      "lid": 2434,
      "signal_ts": "2026-05-04 13:46:31.457820+00:00",
      "setup_name": "Skew Charm",
      "direction": "long",
      "grade": "B",
      "paradigm": "AG-LIS",
      "entry_spx": 7228.95,
      "entry_mes": 7253.75,
      "exit_mes": 7262.5,
      "exit_spx": 7234.99,
      "real_pnl_pts": 8.75,
      "portal_pnl_pts": 6.039999999999964,
      "gap_pts": 2.7100000000000364,
      "portal_event": "trail",
      "real_event": "stop_filled",
      "spx_max_adv": 5.579999999999927,
      "spx_max_fav": 11.039999999999964,
      "mes_max_adv": 54.25,
      "mes_max_fav": 17.25,
      "category": "BASIS_DRIFT",
      "narrative": "Gap=+2.71pt within basis drift threshold.",
      "arch_pnl_pts": 8.75,
      "arch_note": "small basis drift only"
    },
    {
      "lid": 2442,
      "signal_ts": "2026-05-04 14:53:28.568617+00:00",
      "setup_name": "AG Short",
      "direction": "short",
      "grade": "A+",
      "paradigm": "AG-LIS",
      "entry_spx": 7243.11,
      "entry_mes": 7267.75,
      "exit_mes": 7259.25,
      "exit_spx": 7218.77,
      "real_pnl_pts": 8.5,
      "portal_pnl_pts": 24.339999999999236,
      "gap_pts": -15.839999999999236,
      "portal_event": "trail",
      "real_event": "stop_filled",
      "spx_max_adv": 0.32999999999992724,
      "spx_max_fav": 29.339999999999236,
      "mes_max_adv": 3.25,
      "mes_max_fav": 68.25,
      "category": "TRAIL_TAG_FAV_WICK",
      "narrative": "Real trail/BE fired at +8.5pt; SPX path would have run further to trail for +24.3pt. MES wick over-tightened trail.",
      "arch_pnl_pts": 23.839999999999236,
      "arch_note": "SPX-trail market-exit @ portal_event=trail, slippage=0.5pt"
    },
    {
      "lid": 2444,
      "signal_ts": "2026-05-04 14:56:58.510985+00:00",
      "setup_name": "Skew Charm",
      "direction": "long",
      "grade": "B",
      "paradigm": "AG-LIS",
      "entry_spx": 7236.62,
      "entry_mes": 7265.25,
      "exit_mes": 7251.25,
      "exit_spx": 7222.62,
      "real_pnl_pts": -14.0,
      "portal_pnl_pts": -14.0,
      "gap_pts": 0.0,
      "portal_event": "stop",
      "real_event": "stop_filled",
      "spx_max_adv": 22.849999999999454,
      "spx_max_fav": 0.0,
      "mes_max_adv": 65.75,
      "mes_max_fav": 1.5,
      "category": "SL_HIT_BOTH",
      "narrative": "Both initial SL. real=-14.0 portal=-14.0 gap=+0.00",
      "arch_pnl_pts": -14.0,
      "arch_note": "both hit SL \u2014 no change (broker SL still fires)"
    },
    {
      "lid": 2447,
      "signal_ts": "2026-05-04 15:03:01.045759+00:00",
      "setup_name": "Skew Charm",
      "direction": "short",
      "grade": "A",
      "paradigm": "BOFA-PURE",
      "entry_spx": 7234.04,
      "entry_mes": 7261.75,
      "exit_mes": 7253.75,
      "exit_spx": 7218.77,
      "real_pnl_pts": 8.0,
      "portal_pnl_pts": 15.269999999999527,
      "gap_pts": -7.269999999999527,
      "portal_event": "trail",
      "real_event": "stop_filled",
      "spx_max_adv": 0.0,
      "spx_max_fav": 20.269999999999527,
      "mes_max_adv": 2.5,
      "mes_max_fav": 62.25,
      "category": "TRAIL_TAG_FAV_WICK",
      "narrative": "Real trail/BE fired at +8.0pt; SPX path would have run further to trail for +15.3pt. MES wick over-tightened trail.",
      "arch_pnl_pts": 14.769999999999527,
      "arch_note": "SPX-trail market-exit @ portal_event=trail, slippage=0.5pt"
    },
    {
      "lid": 2449,
      "signal_ts": "2026-05-04 15:34:58.525544+00:00",
      "setup_name": "Skew Charm",
      "direction": "short",
      "grade": "A",
      "paradigm": "BOFA-PURE",
      "entry_spx": 7199.71,
      "entry_mes": 7230.0,
      "exit_mes": 7230.25,
      "exit_spx": 7187.36,
      "real_pnl_pts": -0.25,
      "portal_pnl_pts": 12.350000000000364,
      "gap_pts": -12.600000000000364,
      "portal_event": "trail",
      "real_event": "stop_rejected_async",
      "spx_max_adv": 3.4600000000000364,
      "spx_max_fav": 17.350000000000364,
      "mes_max_adv": 9.75,
      "mes_max_fav": 30.5,
      "category": "BUG_STOP_REJECTED",
      "narrative": "Broker rejected stop order async \u2014 bot market-exited at -0.25. Portal would have done +12.35 via trail.",
      "arch_pnl_pts": -0.25,
      "arch_note": "out of scope (broker bug or outcome tracker)"
    },
    {
      "lid": 2466,
      "signal_ts": "2026-05-04 16:48:28.585912+00:00",
      "setup_name": "Skew Charm",
      "direction": "short",
      "grade": "B",
      "paradigm": "BOFA-PURE",
      "entry_spx": 7190.84,
      "entry_mes": 7217.75,
      "exit_mes": 7231.75,
      "exit_spx": 7204.84,
      "real_pnl_pts": -14.0,
      "portal_pnl_pts": -14.0,
      "gap_pts": 0.0,
      "portal_event": "stop",
      "real_event": "stop_filled",
      "spx_max_adv": 14.349999999999454,
      "spx_max_fav": 2.4899999999997817,
      "mes_max_adv": 22.0,
      "mes_max_fav": 4.75,
      "category": "SL_HIT_BOTH",
      "narrative": "Both initial SL. real=-14.0 portal=-14.0 gap=+0.00",
      "arch_pnl_pts": -14.0,
      "arch_note": "both hit SL \u2014 no change (broker SL still fires)"
    },
    {
      "lid": 2470,
      "signal_ts": "2026-05-04 17:18:58.701140+00:00",
      "setup_name": "Skew Charm",
      "direction": "short",
      "grade": "B",
      "paradigm": "BOFA-PURE",
      "entry_spx": 7205.19,
      "entry_mes": 7232.0,
      "exit_mes": 7227.0,
      "exit_spx": 7196.26,
      "real_pnl_pts": 5.0,
      "portal_pnl_pts": 8.929999999999382,
      "gap_pts": -3.9299999999993815,
      "portal_event": "trail",
      "real_event": "ghost_reconcile",
      "spx_max_adv": 7.0700000000006185,
      "spx_max_fav": 13.929999999999382,
      "mes_max_adv": 7.75,
      "mes_max_fav": 14.5,
      "category": "BUG_GHOST_RECONCILE",
      "narrative": "Reconciler-recovered close; bot/broker state diverged. real_pnl=+5.00 portal=+8.93",
      "arch_pnl_pts": 5.0,
      "arch_note": "out of scope (broker bug or outcome tracker)"
    },
    {
      "lid": 2473,
      "signal_ts": "2026-05-04 17:49:31.384492+00:00",
      "setup_name": "VIX Divergence",
      "direction": "long",
      "grade": "A",
      "paradigm": "BOFA-PURE",
      "entry_spx": 7205.83,
      "entry_mes": 7232.5,
      "exit_mes": 7224.5,
      "exit_spx": 7197.83,
      "real_pnl_pts": -8.0,
      "portal_pnl_pts": -8.0,
      "gap_pts": 0.0,
      "portal_event": "stop",
      "real_event": "stop_filled",
      "spx_max_adv": 10.019999999999527,
      "spx_max_fav": 6.430000000000291,
      "mes_max_adv": 15.0,
      "mes_max_fav": 7.25,
      "category": "SL_HIT_BOTH",
      "narrative": "Both initial SL. real=-8.0 portal=-8.0 gap=+0.00",
      "arch_pnl_pts": -8.0,
      "arch_note": "both hit SL \u2014 no change (broker SL still fires)"
    },
    {
      "lid": 2484,
      "signal_ts": "2026-05-04 19:22:58.503349+00:00",
      "setup_name": "Skew Charm",
      "direction": "long",
      "grade": "B",
      "paradigm": "BOFA-PURE",
      "entry_spx": 7201.73,
      "entry_mes": 7226.5,
      "exit_mes": 7225.0,
      "exit_spx": 7199.27,
      "real_pnl_pts": -1.5,
      "portal_pnl_pts": -2.459999999999127,
      "gap_pts": 0.9599999999991269,
      "portal_event": "eod",
      "real_event": "eod_flatten",
      "spx_max_adv": 4.1299999999992,
      "spx_max_fav": 2.7100000000000364,
      "mes_max_adv": 3.25,
      "mes_max_fav": 5.25,
      "category": "BUG_EOD_FLATTEN",
      "narrative": "Held overnight (eod flatten). portal exit_event=eod",
      "arch_pnl_pts": -1.5,
      "arch_note": "out of scope (broker bug or outcome tracker)"
    },
    {
      "lid": 2490,
      "signal_ts": "2026-05-05 14:13:00.075244+00:00",
      "setup_name": "Skew Charm",
      "direction": "short",
      "grade": "A+",
      "paradigm": "AG-PURE",
      "entry_spx": 7254.93,
      "entry_mes": 7279.75,
      "exit_mes": 7274.0,
      "exit_spx": 7248.51,
      "real_pnl_pts": 5.75,
      "portal_pnl_pts": 6.420000000000073,
      "gap_pts": -0.6700000000000728,
      "portal_event": "trail",
      "real_event": "stop_filled",
      "spx_max_adv": 0.0,
      "spx_max_fav": 11.420000000000073,
      "mes_max_adv": 20.25,
      "mes_max_fav": 12.75,
      "category": "BASIS_DRIFT",
      "narrative": "Gap=-0.67pt within basis drift threshold.",
      "arch_pnl_pts": 5.75,
      "arch_note": "small basis drift only"
    },
    {
      "lid": 2492,
      "signal_ts": "2026-05-05 14:18:01.528434+00:00",
      "setup_name": "Skew Charm",
      "direction": "long",
      "grade": "B",
      "paradigm": "AG-LIS",
      "entry_spx": 7242.74,
      "entry_mes": 7276.5,
      "exit_mes": 7281.5,
      "exit_spx": 7252.26,
      "real_pnl_pts": 5.0,
      "portal_pnl_pts": 9.520000000000437,
      "gap_pts": -4.520000000000437,
      "portal_event": "trail",
      "real_event": "stop_filled",
      "spx_max_adv": 0.0,
      "spx_max_fav": 14.520000000000437,
      "mes_max_adv": 9.5,
      "mes_max_fav": 23.5,
      "category": "BASIS_DRIFT",
      "narrative": "Gap=-4.52pt within basis drift threshold.",
      "arch_pnl_pts": 5.0,
      "arch_note": "small basis drift only"
    },
    {
      "lid": 2497,
      "signal_ts": "2026-05-05 14:43:30.141343+00:00",
      "setup_name": "Skew Charm",
      "direction": "short",
      "grade": "A+",
      "paradigm": "BOFA-PURE",
      "entry_spx": 7253.57,
      "entry_mes": 7279.25,
      "exit_mes": 7293.25,
      "exit_spx": 7267.57,
      "real_pnl_pts": -14.0,
      "portal_pnl_pts": -14.0,
      "gap_pts": 0.0,
      "portal_event": "stop",
      "real_event": "stop_filled",
      "spx_max_adv": 14.740000000000691,
      "spx_max_fav": 4.960000000000036,
      "mes_max_adv": 20.75,
      "mes_max_fav": 6.25,
      "category": "SL_HIT_BOTH",
      "narrative": "Both initial SL. real=-14.0 portal=-14.0 gap=+0.00",
      "arch_pnl_pts": -14.0,
      "arch_note": "both hit SL \u2014 no change (broker SL still fires)"
    },
    {
      "lid": 2520,
      "signal_ts": "2026-05-05 19:10:00.113894+00:00",
      "setup_name": "Skew Charm",
      "direction": "long",
      "grade": "B",
      "paradigm": "AG-LIS",
      "entry_spx": 7271.4,
      "entry_mes": 7296.75,
      "exit_mes": 7291.5,
      "exit_spx": 7257.4,
      "real_pnl_pts": -5.25,
      "portal_pnl_pts": -14.0,
      "gap_pts": 8.75,
      "portal_event": "stop",
      "real_event": "eod_flatten",
      "spx_max_adv": 15.009999999999309,
      "spx_max_fav": 1.7000000000007276,
      "mes_max_adv": 14.0,
      "mes_max_fav": 3.25,
      "category": "BUG_EOD_FLATTEN",
      "narrative": "Held overnight (eod flatten). portal exit_event=stop",
      "arch_pnl_pts": -5.25,
      "arch_note": "out of scope (broker bug or outcome tracker)"
    },
    {
      "lid": 2528,
      "signal_ts": "2026-05-06 14:03:44.148847+00:00",
      "setup_name": "Skew Charm",
      "direction": "long",
      "grade": "A+",
      "paradigm": "AG-PURE",
      "entry_spx": 7319.51,
      "entry_mes": 7345.25,
      "exit_mes": 7351.5,
      "exit_spx": 7342.69,
      "real_pnl_pts": 6.25,
      "portal_pnl_pts": 23.17999999999938,
      "gap_pts": -16.92999999999938,
      "portal_event": "trail",
      "real_event": "stop_filled",
      "spx_max_adv": 4.890000000000327,
      "spx_max_fav": 28.17999999999938,
      "mes_max_adv": 8.75,
      "mes_max_fav": 50.75,
      "category": "TRAIL_TAG_FAV_WICK",
      "narrative": "Real trail/BE fired at +6.2pt; SPX path would have run further to trail for +23.2pt. MES wick over-tightened trail.",
      "arch_pnl_pts": 22.67999999999938,
      "arch_note": "SPX-trail market-exit @ portal_event=trail, slippage=0.5pt"
    },
    {
      "lid": 2530,
      "signal_ts": "2026-05-06 14:49:10.125206+00:00",
      "setup_name": "ES Absorption",
      "direction": "bearish",
      "grade": "C",
      "paradigm": "AG-PURE",
      "entry_spx": 7340.14,
      "entry_mes": 7354.5,
      "exit_mes": 7355.0,
      "exit_spx": 7334.91,
      "real_pnl_pts": -0.5,
      "portal_pnl_pts": 5.230000000000473,
      "gap_pts": -5.730000000000473,
      "portal_event": "trail",
      "real_event": "stop_filled",
      "spx_max_adv": 7.549999999999272,
      "spx_max_fav": 8.230000000000473,
      "mes_max_adv": 41.5,
      "mes_max_fav": -0.25,
      "category": "TRAIL_TAG_FAV_WICK",
      "narrative": "Real trail/BE fired at -0.5pt; SPX path would have run further to trail for +5.2pt. MES wick over-tightened trail.",
      "arch_pnl_pts": 4.730000000000473,
      "arch_note": "SPX-trail market-exit @ portal_event=trail, slippage=0.5pt"
    },
    {
      "lid": 2532,
      "signal_ts": "2026-05-06 14:33:09.921967+00:00",
      "setup_name": "AG Short",
      "direction": "short",
      "grade": "A",
      "paradigm": "AG-PURE",
      "entry_spx": 7330.73,
      "entry_mes": 7359.0,
      "exit_mes": 7379.75,
      "exit_spx": 7350.73,
      "real_pnl_pts": -20.75,
      "portal_pnl_pts": -20.0,
      "gap_pts": -0.75,
      "portal_event": "stop",
      "real_event": "LOSS",
      "spx_max_adv": 22.13000000000011,
      "spx_max_fav": 0.0,
      "mes_max_adv": 37.0,
      "mes_max_fav": 4.25,
      "category": "SL_HIT_BOTH",
      "narrative": "Both initial SL. real=-20.8 portal=-20.0 gap=-0.75",
      "arch_pnl_pts": -20.75,
      "arch_note": "both hit SL \u2014 no change (broker SL still fires)"
    },
    {
      "lid": 2540,
      "signal_ts": "2026-05-06 15:17:10.075511+00:00",
      "setup_name": "Skew Charm",
      "direction": "long",
      "grade": "A",
      "paradigm": "BOFA-PURE",
      "entry_spx": 7342.2,
      "entry_mes": 7368.0,
      "exit_mes": 7378.75,
      "exit_spx": 7352.07,
      "real_pnl_pts": 10.75,
      "portal_pnl_pts": 9.86999999999989,
      "gap_pts": 0.8800000000001091,
      "portal_event": "trail",
      "real_event": "stop_filled",
      "spx_max_adv": 10.289999999999964,
      "spx_max_fav": 14.86999999999989,
      "mes_max_adv": 13.25,
      "mes_max_fav": 28.0,
      "category": "BASIS_DRIFT",
      "narrative": "Gap=+0.88pt within basis drift threshold.",
      "arch_pnl_pts": 10.75,
      "arch_note": "small basis drift only"
    },
    {
      "lid": 2565,
      "signal_ts": "2026-05-07 13:50:50.404396+00:00",
      "setup_name": "Skew Charm",
      "direction": "short",
      "grade": "A",
      "paradigm": "BOFA-PURE",
      "entry_spx": 7361.43,
      "entry_mes": 7385.5,
      "exit_mes": 7399.5,
      "exit_spx": 7375.43,
      "real_pnl_pts": -14.0,
      "portal_pnl_pts": -14.0,
      "gap_pts": 0.0,
      "portal_event": "stop",
      "real_event": "stop_filled",
      "spx_max_adv": 14.25,
      "spx_max_fav": 0.0,
      "mes_max_adv": 24.5,
      "mes_max_fav": 39.75,
      "category": "SL_HIT_BOTH",
      "narrative": "Both initial SL. real=-14.0 portal=-14.0 gap=+0.00",
      "arch_pnl_pts": -14.0,
      "arch_note": "both hit SL \u2014 no change (broker SL still fires)"
    },
    {
      "lid": 2575,
      "signal_ts": "2026-05-07 15:01:20.633942+00:00",
      "setup_name": "Skew Charm",
      "direction": "long",
      "grade": "A+",
      "paradigm": "BOFA-PURE",
      "entry_spx": 7383.15,
      "entry_mes": 7407.25,
      "exit_mes": 7393.25,
      "exit_spx": 7369.15,
      "real_pnl_pts": -14.0,
      "portal_pnl_pts": -14.0,
      "gap_pts": 0.0,
      "portal_event": "stop",
      "real_event": "stop_filled",
      "spx_max_adv": 14.779999999999745,
      "spx_max_fav": 0.020000000000436557,
      "mes_max_adv": 61.5,
      "mes_max_fav": 2.75,
      "category": "SL_HIT_BOTH",
      "narrative": "Both initial SL. real=-14.0 portal=-14.0 gap=+0.00",
      "arch_pnl_pts": -14.0,
      "arch_note": "both hit SL \u2014 no change (broker SL still fires)"
    },
    {
      "lid": 2644,
      "signal_ts": "2026-05-08 18:47:30.032622+00:00",
      "setup_name": "ES Absorption",
      "direction": "bullish",
      "grade": "A",
      "paradigm": "BOFA-PURE",
      "entry_spx": 7392.11,
      "entry_mes": 7416.75,
      "exit_mes": 7408.75,
      "exit_spx": 7397.27,
      "real_pnl_pts": -8.0,
      "portal_pnl_pts": 5.160000000000764,
      "gap_pts": -13.160000000000764,
      "portal_event": "eod",
      "real_event": "stop_filled",
      "spx_max_adv": 6.649999999999636,
      "spx_max_fav": 5.160000000000764,
      "mes_max_adv": 9.0,
      "mes_max_fav": 5.5,
      "category": "TRAIL_TAG_ADVERSE_WICK",
      "narrative": "Real broker SL fired (loss -8.0pt) while SPX portal would have exited at eod for +5.2pt. SPX-path max-adv was only 6.6pt vs SL distance 8pt.",
      "arch_pnl_pts": 4.660000000000764,
      "arch_note": "SPX-trail market-exit @ portal_event=eod, slippage=0.5pt"
    },
    {
      "lid": 2646,
      "signal_ts": "2026-05-08 19:04:49.820634+00:00",
      "setup_name": "ES Absorption",
      "direction": "bullish",
      "grade": "A",
      "paradigm": "BOFA-PURE",
      "entry_spx": 7388.28,
      "entry_mes": 7412.75,
      "exit_mes": 7417.75,
      "exit_spx": 7397.27,
      "real_pnl_pts": 5.0,
      "portal_pnl_pts": 8.990000000000691,
      "gap_pts": -3.990000000000691,
      "portal_event": "eod",
      "real_event": "outcome_resolved_win",
      "spx_max_adv": 0.0,
      "spx_max_fav": 8.990000000000691,
      "mes_max_adv": 2.5,
      "mes_max_fav": 9.5,
      "category": "OUTCOME_RESOLVED",
      "narrative": "Outcome tracker resolved (outcome_resolved_win), broker stop never fired. real=5.0 portal=+8.99",
      "arch_pnl_pts": 5.0,
      "arch_note": "out of scope (broker bug or outcome tracker)"
    },
    {
      "lid": 2651,
      "signal_ts": "2026-05-11 13:46:13.329719+00:00",
      "setup_name": "Skew Charm",
      "direction": "short",
      "grade": "A+",
      "paradigm": "GEX-PURE",
      "entry_spx": 7409.76,
      "entry_mes": 7433.5,
      "exit_mes": 7427.0,
      "exit_spx": 7423.76,
      "real_pnl_pts": 6.5,
      "portal_pnl_pts": -14.0,
      "gap_pts": 20.5,
      "portal_event": "stop",
      "real_event": "stop_filled",
      "spx_max_adv": 14.75,
      "spx_max_fav": 6.9099999999998545,
      "mes_max_adv": 21.25,
      "mes_max_fav": 11.75,
      "category": "MES_FAVORABLE",
      "narrative": "Real outperformed SPX path by +20.50pt (MES had bigger favorable swing than SPX showed).",
      "arch_pnl_pts": 6.5,
      "arch_note": "fallback"
    },
    {
      "lid": 2657,
      "signal_ts": "2026-05-11 14:47:43.433871+00:00",
      "setup_name": "Skew Charm",
      "direction": "short",
      "grade": "A+",
      "paradigm": "GEX-PURE",
      "entry_spx": 7411.58,
      "entry_mes": 7435.0,
      "exit_mes": 7449.0,
      "exit_spx": 7425.58,
      "real_pnl_pts": -14.0,
      "portal_pnl_pts": -14.0,
      "gap_pts": 0.0,
      "portal_event": "stop",
      "real_event": "stop_filled",
      "spx_max_adv": 15.430000000000291,
      "spx_max_fav": 2.1899999999996,
      "mes_max_adv": 19.75,
      "mes_max_fav": 7.25,
      "category": "SL_HIT_BOTH",
      "narrative": "Both initial SL. real=-14.0 portal=-14.0 gap=+0.00",
      "arch_pnl_pts": -14.0,
      "arch_note": "both hit SL \u2014 no change (broker SL still fires)"
    },
    {
      "lid": 2684,
      "signal_ts": "2026-05-12 13:47:57.441775+00:00",
      "setup_name": "Skew Charm",
      "direction": "long",
      "grade": "A+",
      "paradigm": "BofA-LIS",
      "entry_spx": 7379.98,
      "entry_mes": 7403.0,
      "exit_mes": 7389.0,
      "exit_spx": 7365.98,
      "real_pnl_pts": -14.0,
      "portal_pnl_pts": -14.0,
      "gap_pts": 0.0,
      "portal_event": "stop",
      "real_event": "stop_filled",
      "spx_max_adv": 19.539999999999964,
      "spx_max_fav": 4.5,
      "mes_max_adv": 39.5,
      "mes_max_fav": 31.0,
      "category": "SL_HIT_BOTH",
      "narrative": "Both initial SL. real=-14.0 portal=-14.0 gap=+0.00",
      "arch_pnl_pts": -14.0,
      "arch_note": "both hit SL \u2014 no change (broker SL still fires)"
    },
    {
      "lid": 2696,
      "signal_ts": "2026-05-12 14:57:28.302875+00:00",
      "setup_name": "Skew Charm",
      "direction": "long",
      "grade": "A+",
      "paradigm": "AG-PURE",
      "entry_spx": 7357.79,
      "entry_mes": 7382.25,
      "exit_mes": 7368.25,
      "exit_spx": 7343.79,
      "real_pnl_pts": -14.0,
      "portal_pnl_pts": -14.0,
      "gap_pts": 0.0,
      "portal_event": "stop",
      "real_event": "ghost_reconcile",
      "spx_max_adv": 18.31999999999971,
      "spx_max_fav": 3.3299999999999272,
      "mes_max_adv": 18.75,
      "mes_max_fav": 51.75,
      "category": "BUG_GHOST_RECONCILE",
      "narrative": "Reconciler-recovered close; bot/broker state diverged. real_pnl=-14.00 portal=-14.00",
      "arch_pnl_pts": -14.0,
      "arch_note": "out of scope (broker bug or outcome tracker)"
    },
    {
      "lid": 2697,
      "signal_ts": "2026-05-12 15:32:51.494017+00:00",
      "setup_name": "ES Absorption",
      "direction": "bullish",
      "grade": "A",
      "paradigm": "AG-PURE",
      "entry_spx": 7348.63,
      "entry_mes": 7371.5,
      "exit_mes": 7376.75,
      "exit_spx": 7354.76,
      "real_pnl_pts": 5.25,
      "portal_pnl_pts": 6.130000000000109,
      "gap_pts": -0.8800000000001091,
      "portal_event": "trail",
      "real_event": "outcome_resolved_win",
      "spx_max_adv": 0.819999999999709,
      "spx_max_fav": 9.13000000000011,
      "mes_max_adv": 7.75,
      "mes_max_fav": 62.5,
      "category": "OUTCOME_RESOLVED",
      "narrative": "Outcome tracker resolved (outcome_resolved_win), broker stop never fired. real=5.25 portal=+6.13",
      "arch_pnl_pts": 5.25,
      "arch_note": "out of scope (broker bug or outcome tracker)"
    },
    {
      "lid": 2705,
      "signal_ts": "2026-05-12 15:58:55.741364+00:00",
      "setup_name": "Skew Charm",
      "direction": "long",
      "grade": "A",
      "paradigm": "BOFA-PURE",
      "entry_spx": 7346.69,
      "entry_mes": 7371.0,
      "exit_mes": 7387.5,
      "exit_spx": 7379.84,
      "real_pnl_pts": 16.5,
      "portal_pnl_pts": 33.150000000000546,
      "gap_pts": -16.650000000000546,
      "portal_event": "trail",
      "real_event": "stop_filled",
      "spx_max_adv": 7.589999999999236,
      "spx_max_fav": 38.150000000000546,
      "mes_max_adv": 7.25,
      "mes_max_fav": 63.0,
      "category": "TRAIL_TAG_FAV_WICK",
      "narrative": "Real trail/BE fired at +16.5pt; SPX path would have run further to trail for +33.2pt. MES wick over-tightened trail.",
      "arch_pnl_pts": 32.650000000000546,
      "arch_note": "SPX-trail market-exit @ portal_event=trail, slippage=0.5pt"
    },
    {
      "lid": 2707,
      "signal_ts": "2026-05-12 16:15:41.716769+00:00",
      "setup_name": "VIX Divergence",
      "direction": "long",
      "grade": "A+",
      "paradigm": "AG-LIS",
      "entry_spx": 7352.49,
      "entry_mes": 7376.75,
      "exit_mes": 7363.75,
      "exit_spx": 7344.49,
      "real_pnl_pts": -13.0,
      "portal_pnl_pts": -8.0,
      "gap_pts": -5.0,
      "portal_event": "stop",
      "real_event": "stop_filled",
      "spx_max_adv": 8.039999999999964,
      "spx_max_fav": 0.7399999999997817,
      "mes_max_adv": 13.0,
      "mes_max_fav": 57.25,
      "category": "SL_HIT_BOTH",
      "narrative": "Both initial SL. real=-13.0 portal=-8.0 gap=-5.00",
      "arch_pnl_pts": -13.0,
      "arch_note": "both hit SL \u2014 no change (broker SL still fires)"
    },
    {
      "lid": 2713,
      "signal_ts": "2026-05-12 17:11:44.657252+00:00",
      "setup_name": "Skew Charm",
      "direction": "long",
      "grade": "B",
      "paradigm": "BOFA-PURE",
      "entry_spx": 7353.2,
      "entry_mes": 7378.0,
      "exit_mes": 7387.75,
      "exit_spx": 7379.84,
      "real_pnl_pts": 9.75,
      "portal_pnl_pts": 26.640000000000327,
      "gap_pts": -16.890000000000327,
      "portal_event": "trail",
      "real_event": "stop_filled",
      "spx_max_adv": 0.5900000000001455,
      "spx_max_fav": 31.640000000000327,
      "mes_max_adv": 3.25,
      "mes_max_fav": 56.0,
      "category": "TRAIL_TAG_FAV_WICK",
      "narrative": "Real trail/BE fired at +9.8pt; SPX path would have run further to trail for +26.6pt. MES wick over-tightened trail.",
      "arch_pnl_pts": 26.140000000000327,
      "arch_note": "SPX-trail market-exit @ portal_event=trail, slippage=0.5pt"
    },
    {
      "lid": 2716,
      "signal_ts": "2026-05-12 17:43:44.572622+00:00",
      "setup_name": "Skew Charm",
      "direction": "long",
      "grade": "B",
      "paradigm": "BOFA-PURE",
      "entry_spx": 7367.96,
      "entry_mes": 7393.5,
      "exit_mes": 7405.25,
      "exit_spx": 7379.84,
      "real_pnl_pts": 11.75,
      "portal_pnl_pts": 11.88000000000011,
      "gap_pts": -0.13000000000010914,
      "portal_event": "trail",
      "real_event": "stop_filled",
      "spx_max_adv": 2.480000000000473,
      "spx_max_fav": 16.88000000000011,
      "mes_max_adv": 4.0,
      "mes_max_fav": 40.5,
      "category": "BASIS_DRIFT",
      "narrative": "Gap=-0.13pt within basis drift threshold.",
      "arch_pnl_pts": 11.75,
      "arch_note": "small basis drift only"
    },
    {
      "lid": 2718,
      "signal_ts": "2026-05-12 18:20:14.904308+00:00",
      "setup_name": "Skew Charm",
      "direction": "long",
      "grade": "A",
      "paradigm": "BOFA-PURE",
      "entry_spx": 7374.64,
      "entry_mes": 7397.75,
      "exit_mes": 7405.0,
      "exit_spx": 7379.84,
      "real_pnl_pts": 7.25,
      "portal_pnl_pts": 5.199999999999818,
      "gap_pts": 2.050000000000182,
      "portal_event": "trail",
      "real_event": "stop_filled",
      "spx_max_adv": 0.0,
      "spx_max_fav": 10.199999999999818,
      "mes_max_adv": 2.5,
      "mes_max_fav": 36.25,
      "category": "BASIS_DRIFT",
      "narrative": "Gap=+2.05pt within basis drift threshold.",
      "arch_pnl_pts": 7.25,
      "arch_note": "small basis drift only"
    },
    {
      "lid": 2726,
      "signal_ts": "2026-05-12 19:20:11.629470+00:00",
      "setup_name": "AG Short",
      "direction": "short",
      "grade": "C",
      "paradigm": "AG-LIS",
      "entry_spx": 7387.66,
      "entry_mes": 7414.0,
      "exit_mes": 7428.75,
      "exit_spx": 7402.41,
      "real_pnl_pts": -14.75,
      "portal_pnl_pts": -14.75,
      "gap_pts": 0.0,
      "portal_event": "stop",
      "real_event": "eod_flatten",
      "spx_max_adv": 17.960000000000036,
      "spx_max_fav": 0.6099999999996726,
      "mes_max_adv": 20.0,
      "mes_max_fav": 3.5,
      "category": "BUG_EOD_FLATTEN",
      "narrative": "Held overnight (eod flatten). portal exit_event=stop",
      "arch_pnl_pts": -14.75,
      "arch_note": "out of scope (broker bug or outcome tracker)"
    },
    {
      "lid": 2728,
      "signal_ts": "2026-05-12 19:24:11.626891+00:00",
      "setup_name": "Skew Charm",
      "direction": "long",
      "grade": "B",
      "paradigm": "AG-LIS",
      "entry_spx": 7391.13,
      "entry_mes": 7413.0,
      "exit_mes": 7421.75,
      "exit_spx": 7403.91,
      "real_pnl_pts": 8.75,
      "portal_pnl_pts": 12.779999999999745,
      "gap_pts": -4.029999999999745,
      "portal_event": "trail",
      "real_event": "ghost_reconcile",
      "spx_max_adv": 0.0,
      "spx_max_fav": 17.779999999999745,
      "mes_max_adv": 2.5,
      "mes_max_fav": 21.0,
      "category": "BUG_GHOST_RECONCILE",
      "narrative": "Reconciler-recovered close; bot/broker state diverged. real_pnl=+8.75 portal=+12.78",
      "arch_pnl_pts": 8.75,
      "arch_note": "out of scope (broker bug or outcome tracker)"
    },
    {
      "lid": 2730,
      "signal_ts": "2026-05-13 13:45:17.280973+00:00",
      "setup_name": "Skew Charm",
      "direction": "long",
      "grade": "A",
      "paradigm": "BOFA-PURE",
      "entry_spx": 7387.39,
      "entry_mes": 7411.25,
      "exit_mes": 7418.0,
      "exit_spx": 7393.94,
      "real_pnl_pts": 6.75,
      "portal_pnl_pts": 6.549999999999272,
      "gap_pts": 0.2000000000007276,
      "portal_event": "trail",
      "real_event": "stop_filled",
      "spx_max_adv": 6.300000000000182,
      "spx_max_fav": 11.549999999999272,
      "mes_max_adv": 12.0,
      "mes_max_fav": 72.75,
      "category": "BASIS_DRIFT",
      "narrative": "Gap=+0.20pt within basis drift threshold.",
      "arch_pnl_pts": 6.75,
      "arch_note": "small basis drift only"
    },
    {
      "lid": 2733,
      "signal_ts": "2026-05-13 14:04:57.223950+00:00",
      "setup_name": "ES Absorption",
      "direction": "bullish",
      "grade": "A",
      "paradigm": "SIDIAL-EXTREME",
      "entry_spx": 7395.73,
      "entry_mes": 7416.5,
      "exit_mes": 7417.25,
      "exit_spx": 7400.8,
      "real_pnl_pts": 0.75,
      "portal_pnl_pts": 5.0700000000006185,
      "gap_pts": -4.3200000000006185,
      "portal_event": "trail",
      "real_event": "ghost_reconcile",
      "spx_max_adv": 3.009999999999309,
      "spx_max_fav": 8.070000000000618,
      "mes_max_adv": 3.0,
      "mes_max_fav": 67.5,
      "category": "BUG_GHOST_RECONCILE",
      "narrative": "Reconciler-recovered close; bot/broker state diverged. real_pnl=+0.75 portal=+5.07",
      "arch_pnl_pts": 0.75,
      "arch_note": "out of scope (broker bug or outcome tracker)"
    },
    {
      "lid": 2735,
      "signal_ts": "2026-05-13 14:12:17.062475+00:00",
      "setup_name": "ES Absorption",
      "direction": "bearish",
      "grade": "A+",
      "paradigm": "SIDIAL-EXTREME",
      "entry_spx": 7396.61,
      "entry_mes": 7414.25,
      "exit_mes": 7430.25,
      "exit_spx": 7404.61,
      "real_pnl_pts": -16.0,
      "portal_pnl_pts": -8.0,
      "gap_pts": -8.0,
      "portal_event": "stop",
      "real_event": "stop_filled",
      "spx_max_adv": 9.510000000000218,
      "spx_max_fav": 3.1599999999998545,
      "mes_max_adv": 69.75,
      "mes_max_fav": 0.0,
      "category": "SL_HIT_BOTH",
      "narrative": "Both initial SL. real=-16.0 portal=-8.0 gap=-8.00",
      "arch_pnl_pts": -16.0,
      "arch_note": "both hit SL \u2014 no change (broker SL still fires)"
    },
    {
      "lid": 2737,
      "signal_ts": "2026-05-13 14:22:12.618271+00:00",
      "setup_name": "ES Absorption",
      "direction": "bearish",
      "grade": "A+",
      "paradigm": "SIDIAL-EXTREME",
      "entry_spx": 7403.8,
      "entry_mes": 7422.0,
      "exit_mes": 7427.5,
      "exit_spx": 7411.8,
      "real_pnl_pts": -5.5,
      "portal_pnl_pts": -8.0,
      "gap_pts": 2.5,
      "portal_event": "stop",
      "real_event": "stop_filled",
      "spx_max_adv": 9.069999999999709,
      "spx_max_fav": 3.2600000000002183,
      "mes_max_adv": 62.0,
      "mes_max_fav": 1.25,
      "category": "BASIS_DRIFT",
      "narrative": "Gap=+2.50pt within basis drift threshold.",
      "arch_pnl_pts": -5.5,
      "arch_note": "small basis drift only"
    },
    {
      "lid": 2740,
      "signal_ts": "2026-05-13 15:42:27.222585+00:00",
      "setup_name": "ES Absorption",
      "direction": "bearish",
      "grade": "A",
      "paradigm": "SIDIAL-EXTREME",
      "entry_spx": 7423.76,
      "entry_mes": 7444.75,
      "exit_mes": 7445.0,
      "exit_spx": 7423.76,
      "real_pnl_pts": -0.25,
      "portal_pnl_pts": 0.0,
      "gap_pts": -0.25,
      "portal_event": "breakeven",
      "real_event": "outcome_resolved_loss",
      "spx_max_adv": 0.0999999999994543,
      "spx_max_fav": 6.400000000000546,
      "mes_max_adv": 39.25,
      "mes_max_fav": 4.75,
      "category": "OUTCOME_RESOLVED",
      "narrative": "Outcome tracker resolved (outcome_resolved_loss), broker stop never fired. real=-0.25 portal=+0.00",
      "arch_pnl_pts": -0.25,
      "arch_note": "out of scope (broker bug or outcome tracker)"
    },
    {
      "lid": 2744,
      "signal_ts": "2026-05-13 15:54:26.497123+00:00",
      "setup_name": "Skew Charm",
      "direction": "long",
      "grade": "A+",
      "paradigm": "BOFA-PURE",
      "entry_spx": 7418.41,
      "entry_mes": 7444.5,
      "exit_mes": 7458.25,
      "exit_spx": 7432.62,
      "real_pnl_pts": 13.75,
      "portal_pnl_pts": 14.210000000000036,
      "gap_pts": -0.4600000000000364,
      "portal_event": "trail",
      "real_event": "stop_filled",
      "spx_max_adv": 1.050000000000182,
      "spx_max_fav": 19.210000000000036,
      "mes_max_adv": 4.5,
      "mes_max_fav": 39.5,
      "category": "BASIS_DRIFT",
      "narrative": "Gap=-0.46pt within basis drift threshold.",
      "arch_pnl_pts": 13.75,
      "arch_note": "small basis drift only"
    },
    {
      "lid": 2748,
      "signal_ts": "2026-05-13 16:28:59.455927+00:00",
      "setup_name": "AG Short",
      "direction": "short",
      "grade": "C",
      "paradigm": "AG-LIS",
      "entry_spx": 7438.62,
      "entry_mes": 7464.25,
      "exit_mes": 7479.0,
      "exit_spx": 7453.37,
      "real_pnl_pts": -14.75,
      "portal_pnl_pts": -14.75,
      "gap_pts": 0.0,
      "portal_event": "stop",
      "real_event": "stop_filled",
      "spx_max_adv": 19.890000000000327,
      "spx_max_fav": 1.5299999999997453,
      "mes_max_adv": 19.75,
      "mes_max_fav": 5.25,
      "category": "SL_HIT_BOTH",
      "narrative": "Both initial SL. real=-14.8 portal=-14.8 gap=+0.00",
      "arch_pnl_pts": -14.75,
      "arch_note": "both hit SL \u2014 no change (broker SL still fires)"
    },
    {
      "lid": 2759,
      "signal_ts": "2026-05-13 18:14:56.430319+00:00",
      "setup_name": "AG Short",
      "direction": "short",
      "grade": "B",
      "paradigm": "AG-LIS",
      "entry_spx": 7458.51,
      "entry_mes": 7478.0,
      "exit_mes": 7482.0,
      "exit_spx": 7451.05,
      "real_pnl_pts": -4.0,
      "portal_pnl_pts": 7.460000000000036,
      "gap_pts": -11.460000000000036,
      "portal_event": "trail",
      "real_event": "ghost_reconcile",
      "spx_max_adv": 0.3899999999994179,
      "spx_max_fav": 12.460000000000036,
      "mes_max_adv": 6.0,
      "mes_max_fav": 11.25,
      "category": "BUG_GHOST_RECONCILE",
      "narrative": "Reconciler-recovered close; bot/broker state diverged. real_pnl=-4.00 portal=+7.46",
      "arch_pnl_pts": -4.0,
      "arch_note": "out of scope (broker bug or outcome tracker)"
    }
  ],
  "skipped": [
    [
      2765,
      "no_chain_data"
    ]
  ]
}